dstwrapper/__init__.py
dstwrapper/api.py
dstwrapper/frame.py
dstwrapper-0.0.4.dist-info/LICENSE
dstwrapper-0.0.4.dist-info/METADATA
dstwrapper-0.0.4.dist-info/WHEEL
dstwrapper-0.0.4.dist-info/top_level.txt
dstwrapper-0.0.4.dist-info/RECORD
