Metadata-Version: 2.1
Name: dstwrapper
Version: 0.0.4
Summary: Python wrapper for Danmarks Statistik API
Home-page: https://github.com/intepa
Author: Emil Sorensen
Author-email: ews@intepa.dk
License: UNKNOWN
Platform: UNKNOWN
Classifier: Programming Language :: Python :: 3
Classifier: License :: OSI Approved :: MIT License
Classifier: Operating System :: OS Independent
Requires-Python: >=3.6
